rf_otp/__init__.py
rf_otp/buildOTP.py
rf_otp-0.1.12.dist-info/LICENSE
rf_otp-0.1.12.dist-info/METADATA
rf_otp-0.1.12.dist-info/WHEEL
rf_otp-0.1.12.dist-info/top_level.txt
rf_otp-0.1.12.dist-info/RECORD
