Metadata-Version: 2.1
Name: rf-otp
Version: 0.1.12
Summary: RobotFramework tools provided by QA team
Home-page: https://argon.ceti.etat-ge.ch/gitlab/performancetests/robotframework/rf-otp
Author: Pedro Lopez Perez
Author-email: Pedro Lopez Perez <pedro.lopez-perez@etat.ge.ch>
Maintainer: Pedro Lopez Perez
License: MIT
Keywords: OTP,TOTP
Requires-Python: >=3.9
License-File: LICENSE
Requires-Dist: pyotp (==2.6.0)
